owmeta/__init__.py
owmeta/bibtex.py
owmeta/bibtex_customizations.py
owmeta/biology.py
owmeta/cell.py
owmeta/cell_common.py
owmeta/channel.py
owmeta/channel_common.py
owmeta/channelworm.py
owmeta/cli_hints.py
owmeta/command.py
owmeta/connection.py
owmeta/document.py
owmeta/documentContext.py
owmeta/evidence.py
owmeta/experiment.py
owmeta/muscle.py
owmeta/my_neuroml.py
owmeta/network.py
owmeta/neuroml.py
owmeta/neuron.py
owmeta/plot.py
owmeta/sources.py
owmeta/translators.py
owmeta/utils.py
owmeta/website.py
owmeta/worm.py
owmeta/worm_common.py
owmeta/commands/__init__.py
owmeta/commands/biology.py
owmeta/data_trans/__init__.py
owmeta/data_trans/bibtex.py
owmeta/data_trans/common_data.py
owmeta/data_trans/connections.py
owmeta/data_trans/context_merge.py
owmeta/data_trans/data_with_evidence_ds.py
owmeta/data_trans/neuron_data.py
owmeta/data_trans/wormatlas.py
owmeta/data_trans/wormbase.py
owmeta-0.12.3.dist-info/LICENSE.txt
owmeta-0.12.3.dist-info/METADATA
owmeta-0.12.3.dist-info/WHEEL
owmeta-0.12.3.dist-info/entry_points.txt
owmeta-0.12.3.dist-info/top_level.txt
owmeta-0.12.3.dist-info/RECORD
