Metadata-Version: 2.1
Name: owmeta
Version: 0.12.3
Summary: A Python library for working with OpenWorm data and models
Home-page: https://owmeta.readthedocs.io/en/latest/
Author: OpenWorm.org authors and contributors
Author-email: info@openworm.org
License: MIT
Download-URL: https://github.com/openworm/owmeta/archive/master.zip
Platform: UNKNOWN
Classifier: Intended Audience :: Science/Research
Classifier: License :: OSI Approved :: BSD License
Classifier: Natural Language :: English
Classifier: Operating System :: OS Independent
Classifier: Programming Language :: Python :: 3.6
Classifier: Programming Language :: Python :: 3.7
Classifier: Programming Language :: Python :: 3.8
Classifier: Topic :: Scientific/Engineering
Requires-Dist: bibtexparser (~=1.1.0)
Requires-Dist: libneuroml
Requires-Dist: owmeta-core
Requires-Dist: rdflib (>=4.1.2)
Requires-Dist: six (~=1.10)
